{
  "type" : "minecraft:crafting_shapeless" ,
  "group" : "nanzhi_grave:iron_ingot",
  "ingredients" : [
    { "item" : "nanzhi_grave:id_tag" },
    { "item" : "nanzhi_grave:id_tag" },
    { "item" : "nanzhi_grave:id_tag" },
    { "item" : "nanzhi_grave:id_tag" },
    { "item" : "nanzhi_grave:id_tag" },
    { "item" : "nanzhi_grave:id_tag" },
    { "item" : "nanzhi_grave:id_tag" },
    { "item" : "nanzhi_grave:id_tag" }
  ] ,
  "result" : {
    "item": "minecraft:iron_ingot",
    "count" : 2
  }
}